vestaboard/__init__.py
vestaboard/base_client.py
vestaboard/client.py
vestaboard/exceptions.py
vestaboard/models.py
vestaboard/py.typed
vestaboard/read_write.py
vestaboard_rw-0.1.1.dist-info/METADATA
vestaboard_rw-0.1.1.dist-info/WHEEL
vestaboard_rw-0.1.1.dist-info/top_level.txt
vestaboard_rw-0.1.1.dist-info/RECORD
