Metadata-Version: 2.4
Name: vestaboard-rw
Version: 0.1.1
Summary: Python client library for Vestaboard Read/Write API
Requires-Python: >=3.9
Requires-Dist: requests>=2.31.0
Requires-Dist: typing-extensions>=4.8.0; python_version < "3.11"
Provides-Extra: dev
Requires-Dist: black>=24.1.0; extra == "dev"
Requires-Dist: flake8>=7.0.0; extra == "dev"
Requires-Dist: isort>=5.13.0; extra == "dev"
Requires-Dist: mypy>=1.8.0; extra == "dev"
Requires-Dist: pydocstyle>=6.3.0; extra == "dev"
Requires-Dist: pytest>=7.4.0; extra == "dev"
Requires-Dist: pytest-cov>=4.1.0; extra == "dev"
Requires-Dist: pytest-mock>=3.12.0; extra == "dev"
Requires-Dist: responses>=0.24.0; extra == "dev"
Requires-Dist: types-requests>=2.31.0.20240106; extra == "dev"
Provides-Extra: dotenv
Requires-Dist: python-dotenv>=1.0.0; extra == "dotenv"
Provides-Extra: docs
Requires-Dist: mkdocs>=1.6.0; extra == "docs"
Requires-Dist: mkdocs-material>=9.5.0; extra == "docs"
Requires-Dist: mkdocstrings[python]>=0.25.0; extra == "docs"
Requires-Dist: pymdown-extensions>=10.0.0; extra == "docs"
